Metadata-Version: 1.0
Name: Jun-distributions
Version: 1.1
Summary: Gaussian and binomial distributions
Home-page: UNKNOWN
Author: Jun Meng
Author-email: jjunmeng@gmail.com
License: UNKNOWN
Platform: UNKNOWN
